zyte_smartproxy_selenium/__init__.py
zyte_smartproxy_selenium/webdriver.py
zyte_smartproxy_selenium/undetected_chromedriver/__init__.py
zyte_smartproxy_selenium/undetected_chromedriver/webdriver.py
Zyte_SmartProxy_Selenium-1.0.8.dist-info/METADATA
Zyte_SmartProxy_Selenium-1.0.8.dist-info/WHEEL
Zyte_SmartProxy_Selenium-1.0.8.dist-info/top_level.txt
Zyte_SmartProxy_Selenium-1.0.8.dist-info/RECORD
