Metadata-Version: 2.1
Name: Zyte-SmartProxy-Selenium
Version: 1.0.8
Summary: A wrapper over Selenium Wire to provide Zyte Smart Proxy Manager specific functionalities.
Home-page: https://github.com/zytedata/zyte-smartproxy-selenium
License: UNKNOWN
Platform: UNKNOWN
Requires-Python: >=3.6
Requires-Dist: adblockparser (>=0.7)
Requires-Dist: requests (>=2.27)
Requires-Dist: selenium-wire (>=4.6)
